MANIFEST.in
README.rst
setup.py
zeroless_tools/SocketExecutor.py
zeroless_tools/__init__.py
zeroless_tools/client.py
zeroless_tools/helpers.py
zeroless_tools/server.py
zeroless_tools.egg-info/PKG-INFO
zeroless_tools.egg-info/SOURCES.txt
zeroless_tools.egg-info/dependency_links.txt
zeroless_tools.egg-info/entry_points.txt
zeroless_tools.egg-info/not-zip-safe
zeroless_tools.egg-info/requires.txt
zeroless_tools.egg-info/top_level.txt