Metadata-Version: 1.1
Name: zeroless-tools
Version: 0.2.2
Summary: CLI Tools for ZeroMQ™
Home-page: https://github.com/zmqless/zeroless-tools
Author: Lucas Lira Gomes
Author-email: x8lucas8x@gmail.com
License: GPLv3
Keywords: pyzmq zeromq zmq ØMQ networking distributed socket client               server p2p publish subscribe request reply push pull               communication internet backend microservices zeroless               python-zeroless cli
Platform: UNKNOWN
Classifier: Development Status :: 4 - Beta
Classifier: Intended Audience :: Developers
Classifier: Programming Language :: Python :: 3
Classifier: Topic :: System :: Networking
Classifier: Topic :: Communications
Classifier: Topic :: Internet
Classifier: Operating System :: MacOS :: MacOS X
Classifier: Operating System :: Microsoft :: Windows
Classifier: Operating System :: POSIX
Classifier: License :: OSI Approved :: GNU General Public License v3 or later (GPLv3+)
